{
  "id": "735-683-N--2020-05-05--13.50.27--detections",
  "model": "ResNet50_COCO_best_v2.0.1.h5",
  "summary": {
    "total": 8,
    "car": 8
  },
  "735-683-N--2020-05-05--13.50.27--detections--1--car--26.8--13x11--186.83v199.94": {
    "type": "car",
    "id": "735-683-N--2020-05-05--13.50.27--detections--1--car--26.8--13x11--186.83v199.94",
    "percentage_probability": 26.754331588745117,
    "box_points": [
      186,
      83,
      199,
      94
    ]
  },
  "735-683-N--2020-05-05--13.50.27--detections--2--car--45.3--11x13--141.87v152.100": {
    "type": "car",
    "id": "735-683-N--2020-05-05--13.50.27--detections--2--car--45.3--11x13--141.87v152.100",
    "percentage_probability": 45.27026414871216,
    "box_points": [
      141,
      87,
      152,
      100
    ]
  },
  "735-683-N--2020-05-05--13.50.27--detections--3--car--45.0--10x12--119.88v129.100": {
    "type": "car",
    "id": "735-683-N--2020-05-05--13.50.27--detections--3--car--45.0--10x12--119.88v129.100",
    "percentage_probability": 45.0438916683197,
    "box_points": [
      119,
      88,
      129,
      100
    ]
  },
  "735-683-N--2020-05-05--13.50.27--detections--4--car--83.6--22x22--172.104v194.126": {
    "type": "car",
    "id": "735-683-N--2020-05-05--13.50.27--detections--4--car--83.6--22x22--172.104v194.126",
    "percentage_probability": 83.61012935638428,
    "box_points": [
      172,
      104,
      194,
      126
    ]
  },
  "735-683-N--2020-05-05--13.50.27--detections--5--car--83.0--29x29--141.108v170.137": {
    "type": "car",
    "id": "735-683-N--2020-05-05--13.50.27--detections--5--car--83.0--29x29--141.108v170.137",
    "percentage_probability": 83.0147385597229,
    "box_points": [
      141,
      108,
      170,
      137
    ]
  },
  "735-683-N--2020-05-05--13.50.27--detections--6--car--83.1--32x30--112.121v144.151": {
    "type": "car",
    "id": "735-683-N--2020-05-05--13.50.27--detections--6--car--83.1--32x30--112.121v144.151",
    "percentage_probability": 83.136647939682,
    "box_points": [
      112,
      121,
      144,
      151
    ]
  },
  "735-683-N--2020-05-05--13.50.27--detections--7--car--90.0--41x34--223.126v264.160": {
    "type": "car",
    "id": "735-683-N--2020-05-05--13.50.27--detections--7--car--90.0--41x34--223.126v264.160",
    "percentage_probability": 90.0338888168335,
    "box_points": [
      223,
      126,
      264,
      160
    ]
  },
  "735-683-N--2020-05-05--13.50.27--detections--8--car--68.0--86x31--176.206v262.237": {
    "type": "car",
    "id": "735-683-N--2020-05-05--13.50.27--detections--8--car--68.0--86x31--176.206v262.237",
    "percentage_probability": 67.95105934143066,
    "box_points": [
      176,
      206,
      262,
      237
    ]
  }
}
