{
  "id": "735-683-N--2020-05-05--13.30.21--detections",
  "model": "ResNet50_COCO_best_v2.0.1.h5",
  "summary": {
    "total": 11,
    "car": 10,
    "bus": 1
  },
  "735-683-N--2020-05-05--13.30.21--detections--1--car--28.0--11x8--195.75v206.83": {
    "type": "car",
    "id": "735-683-N--2020-05-05--13.30.21--detections--1--car--28.0--11x8--195.75v206.83",
    "percentage_probability": 27.99798548221588,
    "box_points": [
      195,
      75,
      206,
      83
    ]
  },
  "735-683-N--2020-05-05--13.30.21--detections--2--car--40.1--10x10--174.81v184.91": {
    "type": "car",
    "id": "735-683-N--2020-05-05--13.30.21--detections--2--car--40.1--10x10--174.81v184.91",
    "percentage_probability": 40.085285902023315,
    "box_points": [
      174,
      81,
      184,
      91
    ]
  },
  "735-683-N--2020-05-05--13.30.21--detections--3--car--40.5--14x12--191.82v205.94": {
    "type": "car",
    "id": "735-683-N--2020-05-05--13.30.21--detections--3--car--40.5--14x12--191.82v205.94",
    "percentage_probability": 40.524131059646606,
    "box_points": [
      191,
      82,
      205,
      94
    ]
  },
  "735-683-N--2020-05-05--13.30.21--detections--4--bus--28.4--17x18--143.89v160.107": {
    "type": "bus",
    "id": "735-683-N--2020-05-05--13.30.21--detections--4--bus--28.4--17x18--143.89v160.107",
    "percentage_probability": 28.432980179786682,
    "box_points": [
      143,
      89,
      160,
      107
    ]
  },
  "735-683-N--2020-05-05--13.30.21--detections--5--car--29.5--19x19--121.90v140.109": {
    "type": "car",
    "id": "735-683-N--2020-05-05--13.30.21--detections--5--car--29.5--19x19--121.90v140.109",
    "percentage_probability": 29.535052180290222,
    "box_points": [
      121,
      90,
      140,
      109
    ]
  },
  "735-683-N--2020-05-05--13.30.21--detections--6--car--40.6--17x16--143.91v160.107": {
    "type": "car",
    "id": "735-683-N--2020-05-05--13.30.21--detections--6--car--40.6--17x16--143.91v160.107",
    "percentage_probability": 40.62715172767639,
    "box_points": [
      143,
      91,
      160,
      107
    ]
  },
  "735-683-N--2020-05-05--13.30.21--detections--7--car--61.7--22x24--106.104v128.128": {
    "type": "car",
    "id": "735-683-N--2020-05-05--13.30.21--detections--7--car--61.7--22x24--106.104v128.128",
    "percentage_probability": 61.656880378723145,
    "box_points": [
      106,
      104,
      128,
      128
    ]
  },
  "735-683-N--2020-05-05--13.30.21--detections--8--car--66.4--35x34--142.108v177.142": {
    "type": "car",
    "id": "735-683-N--2020-05-05--13.30.21--detections--8--car--66.4--35x34--142.108v177.142",
    "percentage_probability": 66.41464233398438,
    "box_points": [
      142,
      108,
      177,
      142
    ]
  },
  "735-683-N--2020-05-05--13.30.21--detections--9--car--94.8--61x50--284.147v345.197": {
    "type": "car",
    "id": "735-683-N--2020-05-05--13.30.21--detections--9--car--94.8--61x50--284.147v345.197",
    "percentage_probability": 94.80836391448975,
    "box_points": [
      284,
      147,
      345,
      197
    ]
  },
  "735-683-N--2020-05-05--13.30.21--detections--10--car--79.6--78x75--141.162v219.237": {
    "type": "car",
    "id": "735-683-N--2020-05-05--13.30.21--detections--10--car--79.6--78x75--141.162v219.237",
    "percentage_probability": 79.62555885314941,
    "box_points": [
      141,
      162,
      219,
      237
    ]
  },
  "735-683-N--2020-05-05--13.30.21--detections--11--car--80.7--65x73--204.126v269.199": {
    "type": "car",
    "id": "735-683-N--2020-05-05--13.30.21--detections--11--car--80.7--65x73--204.126v269.199",
    "percentage_probability": 80.70476651191711,
    "box_points": [
      204,
      126,
      269,
      199
    ]
  }
}
