{
  "id": "735-683-N--2020-05-05--13.27.27--detections",
  "model": "ResNet50_COCO_best_v2.0.1.h5",
  "summary": {
    "total": 5,
    "car": 4,
    "bus": 1
  },
  "735-683-N--2020-05-05--13.27.27--detections--1--car--27.3--8x10--110.80v118.90": {
    "type": "car",
    "id": "735-683-N--2020-05-05--13.27.27--detections--1--car--27.3--8x10--110.80v118.90",
    "percentage_probability": 27.262741327285767,
    "box_points": [
      110,
      80,
      118,
      90
    ]
  },
  "735-683-N--2020-05-05--13.27.27--detections--2--car--82.4--12x10--188.87v200.97": {
    "type": "car",
    "id": "735-683-N--2020-05-05--13.27.27--detections--2--car--82.4--12x10--188.87v200.97",
    "percentage_probability": 82.40468502044678,
    "box_points": [
      188,
      87,
      200,
      97
    ]
  },
  "735-683-N--2020-05-05--13.27.27--detections--3--car--37.9--21x20--50.100v71.120": {
    "type": "car",
    "id": "735-683-N--2020-05-05--13.27.27--detections--3--car--37.9--21x20--50.100v71.120",
    "percentage_probability": 37.88299560546875,
    "box_points": [
      50,
      100,
      71,
      120
    ]
  },
  "735-683-N--2020-05-05--13.27.27--detections--4--bus--35.2--21x20--50.100v71.120": {
    "type": "bus",
    "id": "735-683-N--2020-05-05--13.27.27--detections--4--bus--35.2--21x20--50.100v71.120",
    "percentage_probability": 35.248687863349915,
    "box_points": [
      50,
      100,
      71,
      120
    ]
  },
  "735-683-N--2020-05-05--13.27.27--detections--5--car--92.0--82x51--266.185v348.236": {
    "type": "car",
    "id": "735-683-N--2020-05-05--13.27.27--detections--5--car--92.0--82x51--266.185v348.236",
    "percentage_probability": 92.02377796173096,
    "box_points": [
      266,
      185,
      348,
      236
    ]
  }
}
