{
  "id": "735-683-N--2020-05-05--13.23.22--detections",
  "model": "ResNet50_COCO_best_v2.0.1.h5",
  "summary": {
    "total": 9,
    "car": 8,
    "bus": 1
  },
  "735-683-N--2020-05-05--13.23.22--detections--1--car--42.1--10x7--168.81v178.88": {
    "type": "car",
    "id": "735-683-N--2020-05-05--13.23.22--detections--1--car--42.1--10x7--168.81v178.88",
    "percentage_probability": 42.069584131240845,
    "box_points": [
      168,
      81,
      178,
      88
    ]
  },
  "735-683-N--2020-05-05--13.23.22--detections--2--car--32.8--9x11--118.86v127.97": {
    "type": "car",
    "id": "735-683-N--2020-05-05--13.23.22--detections--2--car--32.8--9x11--118.86v127.97",
    "percentage_probability": 32.847005128860474,
    "box_points": [
      118,
      86,
      127,
      97
    ]
  },
  "735-683-N--2020-05-05--13.23.22--detections--3--car--25.6--9x10--137.86v146.96": {
    "type": "car",
    "id": "735-683-N--2020-05-05--13.23.22--detections--3--car--25.6--9x10--137.86v146.96",
    "percentage_probability": 25.56616961956024,
    "box_points": [
      137,
      86,
      146,
      96
    ]
  },
  "735-683-N--2020-05-05--13.23.22--detections--4--car--39.6--16x14--146.99v162.113": {
    "type": "car",
    "id": "735-683-N--2020-05-05--13.23.22--detections--4--car--39.6--16x14--146.99v162.113",
    "percentage_probability": 39.602696895599365,
    "box_points": [
      146,
      99,
      162,
      113
    ]
  },
  "735-683-N--2020-05-05--13.23.22--detections--5--car--31.3--12x9--150.104v162.113": {
    "type": "car",
    "id": "735-683-N--2020-05-05--13.23.22--detections--5--car--31.3--12x9--150.104v162.113",
    "percentage_probability": 31.331753730773926,
    "box_points": [
      150,
      104,
      162,
      113
    ]
  },
  "735-683-N--2020-05-05--13.23.22--detections--6--car--55.4--20x21--131.99v151.120": {
    "type": "car",
    "id": "735-683-N--2020-05-05--13.23.22--detections--6--car--55.4--20x21--131.99v151.120",
    "percentage_probability": 55.407994985580444,
    "box_points": [
      131,
      99,
      151,
      120
    ]
  },
  "735-683-N--2020-05-05--13.23.22--detections--7--car--26.3--24x17--135.99v159.116": {
    "type": "car",
    "id": "735-683-N--2020-05-05--13.23.22--detections--7--car--26.3--24x17--135.99v159.116",
    "percentage_probability": 26.321017742156982,
    "box_points": [
      135,
      99,
      159,
      116
    ]
  },
  "735-683-N--2020-05-05--13.23.22--detections--8--car--29.8--24x24--167.101v191.125": {
    "type": "car",
    "id": "735-683-N--2020-05-05--13.23.22--detections--8--car--29.8--24x24--167.101v191.125",
    "percentage_probability": 29.770374298095703,
    "box_points": [
      167,
      101,
      191,
      125
    ]
  },
  "735-683-N--2020-05-05--13.23.22--detections--9--bus--77.5--24x23--167.101v191.124": {
    "type": "bus",
    "id": "735-683-N--2020-05-05--13.23.22--detections--9--bus--77.5--24x23--167.101v191.124",
    "percentage_probability": 77.51162052154541,
    "box_points": [
      167,
      101,
      191,
      124
    ]
  }
}
