{
  "id": "735-683-N--2020-05-05--13.38.00--detections",
  "model": "ResNet50_COCO_best_v2.0.1.h5",
  "summary": {
    "total": 8,
    "car": 8
  },
  "735-683-N--2020-05-05--13.38.00--detections--1--car--26.9--9x10--131.82v140.92": {
    "type": "car",
    "id": "735-683-N--2020-05-05--13.38.00--detections--1--car--26.9--9x10--131.82v140.92",
    "percentage_probability": 26.879113912582397,
    "box_points": [
      131,
      82,
      140,
      92
    ]
  },
  "735-683-N--2020-05-05--13.38.00--detections--2--car--28.1--12x11--168.81v180.92": {
    "type": "car",
    "id": "735-683-N--2020-05-05--13.38.00--detections--2--car--28.1--12x11--168.81v180.92",
    "percentage_probability": 28.12802791595459,
    "box_points": [
      168,
      81,
      180,
      92
    ]
  },
  "735-683-N--2020-05-05--13.38.00--detections--3--car--44.3--10x9--156.83v166.92": {
    "type": "car",
    "id": "735-683-N--2020-05-05--13.38.00--detections--3--car--44.3--10x9--156.83v166.92",
    "percentage_probability": 44.30510401725769,
    "box_points": [
      156,
      83,
      166,
      92
    ]
  },
  "735-683-N--2020-05-05--13.38.00--detections--4--car--50.6--10x10--120.88v130.98": {
    "type": "car",
    "id": "735-683-N--2020-05-05--13.38.00--detections--4--car--50.6--10x10--120.88v130.98",
    "percentage_probability": 50.57085156440735,
    "box_points": [
      120,
      88,
      130,
      98
    ]
  },
  "735-683-N--2020-05-05--13.38.00--detections--5--car--49.2--11x14--142.88v153.102": {
    "type": "car",
    "id": "735-683-N--2020-05-05--13.38.00--detections--5--car--49.2--11x14--142.88v153.102",
    "percentage_probability": 49.16942119598389,
    "box_points": [
      142,
      88,
      153,
      102
    ]
  },
  "735-683-N--2020-05-05--13.38.00--detections--6--car--30.4--19x19--48.100v67.119": {
    "type": "car",
    "id": "735-683-N--2020-05-05--13.38.00--detections--6--car--30.4--19x19--48.100v67.119",
    "percentage_probability": 30.417340993881226,
    "box_points": [
      48,
      100,
      67,
      119
    ]
  },
  "735-683-N--2020-05-05--13.38.00--detections--7--car--87.7--40x36--176.127v216.163": {
    "type": "car",
    "id": "735-683-N--2020-05-05--13.38.00--detections--7--car--87.7--40x36--176.127v216.163",
    "percentage_probability": 87.68225908279419,
    "box_points": [
      176,
      127,
      216,
      163
    ]
  },
  "735-683-N--2020-05-05--13.38.00--detections--8--car--62.6--37x78--315.143v352.221": {
    "type": "car",
    "id": "735-683-N--2020-05-05--13.38.00--detections--8--car--62.6--37x78--315.143v352.221",
    "percentage_probability": 62.597060203552246,
    "box_points": [
      315,
      143,
      352,
      221
    ]
  }
}
