{
  "id": "735-683-N--2020-05-05--13.40.01--detections",
  "model": "ResNet50_COCO_best_v2.0.1.h5",
  "summary": {
    "total": 16,
    "car": 16
  },
  "735-683-N--2020-05-05--13.40.01--detections--1--car--28.3--12x13--139.87v151.100": {
    "type": "car",
    "id": "735-683-N--2020-05-05--13.40.01--detections--1--car--28.3--12x13--139.87v151.100",
    "percentage_probability": 28.29907536506653,
    "box_points": [
      139,
      87,
      151,
      100
    ]
  },
  "735-683-N--2020-05-05--13.40.01--detections--2--car--42.0--10x10--122.96v132.106": {
    "type": "car",
    "id": "735-683-N--2020-05-05--13.40.01--detections--2--car--42.0--10x10--122.96v132.106",
    "percentage_probability": 42.02112555503845,
    "box_points": [
      122,
      96,
      132,
      106
    ]
  },
  "735-683-N--2020-05-05--13.40.01--detections--3--car--32.4--14x12--123.95v137.107": {
    "type": "car",
    "id": "735-683-N--2020-05-05--13.40.01--detections--3--car--32.4--14x12--123.95v137.107",
    "percentage_probability": 32.35540986061096,
    "box_points": [
      123,
      95,
      137,
      107
    ]
  },
  "735-683-N--2020-05-05--13.40.01--detections--4--car--64.3--15x13--128.96v143.109": {
    "type": "car",
    "id": "735-683-N--2020-05-05--13.40.01--detections--4--car--64.3--15x13--128.96v143.109",
    "percentage_probability": 64.33947086334229,
    "box_points": [
      128,
      96,
      143,
      109
    ]
  },
  "735-683-N--2020-05-05--13.40.01--detections--5--car--52.4--18x16--155.100v173.116": {
    "type": "car",
    "id": "735-683-N--2020-05-05--13.40.01--detections--5--car--52.4--18x16--155.100v173.116",
    "percentage_probability": 52.422404289245605,
    "box_points": [
      155,
      100,
      173,
      116
    ]
  },
  "735-683-N--2020-05-05--13.40.01--detections--6--car--46.5--18x15--174.101v192.116": {
    "type": "car",
    "id": "735-683-N--2020-05-05--13.40.01--detections--6--car--46.5--18x15--174.101v192.116",
    "percentage_probability": 46.54650688171387,
    "box_points": [
      174,
      101,
      192,
      116
    ]
  },
  "735-683-N--2020-05-05--13.40.01--detections--7--car--31.0--24x21--172.103v196.124": {
    "type": "car",
    "id": "735-683-N--2020-05-05--13.40.01--detections--7--car--31.0--24x21--172.103v196.124",
    "percentage_probability": 30.998623371124268,
    "box_points": [
      172,
      103,
      196,
      124
    ]
  },
  "735-683-N--2020-05-05--13.40.01--detections--8--car--47.2--23x24--111.107v134.131": {
    "type": "car",
    "id": "735-683-N--2020-05-05--13.40.01--detections--8--car--47.2--23x24--111.107v134.131",
    "percentage_probability": 47.18247652053833,
    "box_points": [
      111,
      107,
      134,
      131
    ]
  },
  "735-683-N--2020-05-05--13.40.01--detections--9--car--46.9--20x17--137.108v157.125": {
    "type": "car",
    "id": "735-683-N--2020-05-05--13.40.01--detections--9--car--46.9--20x17--137.108v157.125",
    "percentage_probability": 46.88989818096161,
    "box_points": [
      137,
      108,
      157,
      125
    ]
  },
  "735-683-N--2020-05-05--13.40.01--detections--10--car--83.3--27x24--173.109v200.133": {
    "type": "car",
    "id": "735-683-N--2020-05-05--13.40.01--detections--10--car--83.3--27x24--173.109v200.133",
    "percentage_probability": 83.27030539512634,
    "box_points": [
      173,
      109,
      200,
      133
    ]
  },
  "735-683-N--2020-05-05--13.40.01--detections--11--car--37.6--31x27--113.110v144.137": {
    "type": "car",
    "id": "735-683-N--2020-05-05--13.40.01--detections--11--car--37.6--31x27--113.110v144.137",
    "percentage_probability": 37.626856565475464,
    "box_points": [
      113,
      110,
      144,
      137
    ]
  },
  "735-683-N--2020-05-05--13.40.01--detections--12--car--52.5--36x40--113.116v149.156": {
    "type": "car",
    "id": "735-683-N--2020-05-05--13.40.01--detections--12--car--52.5--36x40--113.116v149.156",
    "percentage_probability": 52.48553156852722,
    "box_points": [
      113,
      116,
      149,
      156
    ]
  },
  "735-683-N--2020-05-05--13.40.01--detections--13--car--80.1--30x29--216.124v246.153": {
    "type": "car",
    "id": "735-683-N--2020-05-05--13.40.01--detections--13--car--80.1--30x29--216.124v246.153",
    "percentage_probability": 80.11160492897034,
    "box_points": [
      216,
      124,
      246,
      153
    ]
  },
  "735-683-N--2020-05-05--13.40.01--detections--14--car--35.8--36x28--207.131v243.159": {
    "type": "car",
    "id": "735-683-N--2020-05-05--13.40.01--detections--14--car--35.8--36x28--207.131v243.159",
    "percentage_probability": 35.79748272895813,
    "box_points": [
      207,
      131,
      243,
      159
    ]
  },
  "735-683-N--2020-05-05--13.40.01--detections--15--car--95.1--49x42--192.136v241.178": {
    "type": "car",
    "id": "735-683-N--2020-05-05--13.40.01--detections--15--car--95.1--49x42--192.136v241.178",
    "percentage_probability": 95.09319067001343,
    "box_points": [
      192,
      136,
      241,
      178
    ]
  },
  "735-683-N--2020-05-05--13.40.01--detections--16--car--92.0--82x29--267.209v349.238": {
    "type": "car",
    "id": "735-683-N--2020-05-05--13.40.01--detections--16--car--92.0--82x29--267.209v349.238",
    "percentage_probability": 92.0195460319519,
    "box_points": [
      267,
      209,
      349,
      238
    ]
  }
}
