{
  "id": "735-683-N--2020-05-05--13.39.12--detections",
  "model": "ResNet50_COCO_best_v2.0.1.h5",
  "summary": {
    "total": 8,
    "car": 7,
    "bus": 1
  },
  "735-683-N--2020-05-05--13.39.12--detections--1--car--26.6--12x14--143.89v155.103": {
    "type": "car",
    "id": "735-683-N--2020-05-05--13.39.12--detections--1--car--26.6--12x14--143.89v155.103",
    "percentage_probability": 26.627624034881592,
    "box_points": [
      143,
      89,
      155,
      103
    ]
  },
  "735-683-N--2020-05-05--13.39.12--detections--2--car--36.3--18x22--127.92v145.114": {
    "type": "car",
    "id": "735-683-N--2020-05-05--13.39.12--detections--2--car--36.3--18x22--127.92v145.114",
    "percentage_probability": 36.31877899169922,
    "box_points": [
      127,
      92,
      145,
      114
    ]
  },
  "735-683-N--2020-05-05--13.39.12--detections--3--car--41.0--16x13--127.102v143.115": {
    "type": "car",
    "id": "735-683-N--2020-05-05--13.39.12--detections--3--car--41.0--16x13--127.102v143.115",
    "percentage_probability": 41.043904423713684,
    "box_points": [
      127,
      102,
      143,
      115
    ]
  },
  "735-683-N--2020-05-05--13.39.12--detections--4--bus--35.7--18x24--127.89v145.113": {
    "type": "bus",
    "id": "735-683-N--2020-05-05--13.39.12--detections--4--bus--35.7--18x24--127.89v145.113",
    "percentage_probability": 35.65647304058075,
    "box_points": [
      127,
      89,
      145,
      113
    ]
  },
  "735-683-N--2020-05-05--13.39.12--detections--5--car--39.4--17x19--157.95v174.114": {
    "type": "car",
    "id": "735-683-N--2020-05-05--13.39.12--detections--5--car--39.4--17x19--157.95v174.114",
    "percentage_probability": 39.368945360183716,
    "box_points": [
      157,
      95,
      174,
      114
    ]
  },
  "735-683-N--2020-05-05--13.39.12--detections--6--car--83.4--22x21--138.103v160.124": {
    "type": "car",
    "id": "735-683-N--2020-05-05--13.39.12--detections--6--car--83.4--22x21--138.103v160.124",
    "percentage_probability": 83.3549439907074,
    "box_points": [
      138,
      103,
      160,
      124
    ]
  },
  "735-683-N--2020-05-05--13.39.12--detections--7--car--82.0--40x18--1.109v41.127": {
    "type": "car",
    "id": "735-683-N--2020-05-05--13.39.12--detections--7--car--82.0--40x18--1.109v41.127",
    "percentage_probability": 82.04195499420166,
    "box_points": [
      1,
      109,
      41,
      127
    ]
  },
  "735-683-N--2020-05-05--13.39.12--detections--8--car--90.7--36x37--192.109v228.146": {
    "type": "car",
    "id": "735-683-N--2020-05-05--13.39.12--detections--8--car--90.7--36x37--192.109v228.146",
    "percentage_probability": 90.74706435203552,
    "box_points": [
      192,
      109,
      228,
      146
    ]
  }
}
