{
  "id": "735-683-N--2020-05-05--13.54.42--detections",
  "model": "ResNet50_COCO_best_v2.0.1.h5",
  "summary": {
    "total": 8,
    "car": 8
  },
  "735-683-N--2020-05-05--13.54.42--detections--1--car--29.6--8x8--128.76v136.84": {
    "type": "car",
    "id": "735-683-N--2020-05-05--13.54.42--detections--1--car--29.6--8x8--128.76v136.84",
    "percentage_probability": 29.64818775653839,
    "box_points": [
      128,
      76,
      136,
      84
    ]
  },
  "735-683-N--2020-05-05--13.54.42--detections--2--car--28.3--12x9--110.77v122.86": {
    "type": "car",
    "id": "735-683-N--2020-05-05--13.54.42--detections--2--car--28.3--12x9--110.77v122.86",
    "percentage_probability": 28.31399142742157,
    "box_points": [
      110,
      77,
      122,
      86
    ]
  },
  "735-683-N--2020-05-05--13.54.42--detections--3--car--27.9--13x12--111.80v124.92": {
    "type": "car",
    "id": "735-683-N--2020-05-05--13.54.42--detections--3--car--27.9--13x12--111.80v124.92",
    "percentage_probability": 27.947649359703064,
    "box_points": [
      111,
      80,
      124,
      92
    ]
  },
  "735-683-N--2020-05-05--13.54.42--detections--4--car--35.0--8x8--128.83v136.91": {
    "type": "car",
    "id": "735-683-N--2020-05-05--13.54.42--detections--4--car--35.0--8x8--128.83v136.91",
    "percentage_probability": 34.99978482723236,
    "box_points": [
      128,
      83,
      136,
      91
    ]
  },
  "735-683-N--2020-05-05--13.54.42--detections--5--car--32.9--21x17--160.72v181.89": {
    "type": "car",
    "id": "735-683-N--2020-05-05--13.54.42--detections--5--car--32.9--21x17--160.72v181.89",
    "percentage_probability": 32.86912441253662,
    "box_points": [
      160,
      72,
      181,
      89
    ]
  },
  "735-683-N--2020-05-05--13.54.42--detections--6--car--74.0--31x27--148.115v179.142": {
    "type": "car",
    "id": "735-683-N--2020-05-05--13.54.42--detections--6--car--74.0--31x27--148.115v179.142",
    "percentage_probability": 74.02046322822571,
    "box_points": [
      148,
      115,
      179,
      142
    ]
  },
  "735-683-N--2020-05-05--13.54.42--detections--7--car--84.9--53x54--188.128v241.182": {
    "type": "car",
    "id": "735-683-N--2020-05-05--13.54.42--detections--7--car--84.9--53x54--188.128v241.182",
    "percentage_probability": 84.85205173492432,
    "box_points": [
      188,
      128,
      241,
      182
    ]
  },
  "735-683-N--2020-05-05--13.54.42--detections--8--car--96.7--58x46--268.140v326.186": {
    "type": "car",
    "id": "735-683-N--2020-05-05--13.54.42--detections--8--car--96.7--58x46--268.140v326.186",
    "percentage_probability": 96.66891098022461,
    "box_points": [
      268,
      140,
      326,
      186
    ]
  }
}
