{
  "id": "735-683-N--2020-05-05--13.18.43--detections",
  "model": "ResNet50_COCO_best_v2.0.1.h5",
  "summary": {
    "total": 3,
    "car": 3
  },
  "735-683-N--2020-05-05--13.18.43--detections--1--car--79.2--22x20--119.105v141.125": {
    "type": "car",
    "id": "735-683-N--2020-05-05--13.18.43--detections--1--car--79.2--22x20--119.105v141.125",
    "percentage_probability": 79.19954061508179,
    "box_points": [
      119,
      105,
      141,
      125
    ]
  },
  "735-683-N--2020-05-05--13.18.43--detections--2--car--82.9--30x26--144.114v174.140": {
    "type": "car",
    "id": "735-683-N--2020-05-05--13.18.43--detections--2--car--82.9--30x26--144.114v174.140",
    "percentage_probability": 82.90948867797852,
    "box_points": [
      144,
      114,
      174,
      140
    ]
  },
  "735-683-N--2020-05-05--13.18.43--detections--3--car--77.1--40x63--312.154v352.217": {
    "type": "car",
    "id": "735-683-N--2020-05-05--13.18.43--detections--3--car--77.1--40x63--312.154v352.217",
    "percentage_probability": 77.08827257156372,
    "box_points": [
      312,
      154,
      352,
      217
    ]
  }
}
