{
  "id": "735-683-N--2020-05-05--13.14.57--detections",
  "model": "ResNet50_COCO_best_v2.0.1.h5",
  "summary": {
    "total": 2,
    "car": 2
  },
  "735-683-N--2020-05-05--13.14.57--detections--1--car--25.5--9x12--131.81v140.93": {
    "type": "car",
    "id": "735-683-N--2020-05-05--13.14.57--detections--1--car--25.5--9x12--131.81v140.93",
    "percentage_probability": 25.535422563552856,
    "box_points": [
      131,
      81,
      140,
      93
    ]
  },
  "735-683-N--2020-05-05--13.14.57--detections--2--car--41.7--12x12--122.92v134.104": {
    "type": "car",
    "id": "735-683-N--2020-05-05--13.14.57--detections--2--car--41.7--12x12--122.92v134.104",
    "percentage_probability": 41.67076349258423,
    "box_points": [
      122,
      92,
      134,
      104
    ]
  }
}
