{
  "id": "735-683-N--2020-05-05--13.10.23--detections",
  "model": "ResNet50_COCO_best_v2.0.1.h5",
  "summary": {
    "total": 12,
    "car": 11,
    "bus": 1
  },
  "735-683-N--2020-05-05--13.10.23--detections--1--car--50.8--9x9--112.81v121.90": {
    "type": "car",
    "id": "735-683-N--2020-05-05--13.10.23--detections--1--car--50.8--9x9--112.81v121.90",
    "percentage_probability": 50.78440308570862,
    "box_points": [
      112,
      81,
      121,
      90
    ]
  },
  "735-683-N--2020-05-05--13.10.23--detections--2--car--45.6--11x12--121.89v132.101": {
    "type": "car",
    "id": "735-683-N--2020-05-05--13.10.23--detections--2--car--45.6--11x12--121.89v132.101",
    "percentage_probability": 45.584267377853394,
    "box_points": [
      121,
      89,
      132,
      101
    ]
  },
  "735-683-N--2020-05-05--13.10.23--detections--3--car--26.4--10x9--139.94v149.103": {
    "type": "car",
    "id": "735-683-N--2020-05-05--13.10.23--detections--3--car--26.4--10x9--139.94v149.103",
    "percentage_probability": 26.372164487838745,
    "box_points": [
      139,
      94,
      149,
      103
    ]
  },
  "735-683-N--2020-05-05--13.10.23--detections--4--car--33.3--13x13--131.101v144.114": {
    "type": "car",
    "id": "735-683-N--2020-05-05--13.10.23--detections--4--car--33.3--13x13--131.101v144.114",
    "percentage_probability": 33.26951563358307,
    "box_points": [
      131,
      101,
      144,
      114
    ]
  },
  "735-683-N--2020-05-05--13.10.23--detections--5--car--41.4--15x14--113.95v128.109": {
    "type": "car",
    "id": "735-683-N--2020-05-05--13.10.23--detections--5--car--41.4--15x14--113.95v128.109",
    "percentage_probability": 41.40978157520294,
    "box_points": [
      113,
      95,
      128,
      109
    ]
  },
  "735-683-N--2020-05-05--13.10.23--detections--6--car--85.5--21x17--50.104v71.121": {
    "type": "car",
    "id": "735-683-N--2020-05-05--13.10.23--detections--6--car--85.5--21x17--50.104v71.121",
    "percentage_probability": 85.54338812828064,
    "box_points": [
      50,
      104,
      71,
      121
    ]
  },
  "735-683-N--2020-05-05--13.10.23--detections--7--car--56.5--24x25--137.104v161.129": {
    "type": "car",
    "id": "735-683-N--2020-05-05--13.10.23--detections--7--car--56.5--24x25--137.104v161.129",
    "percentage_probability": 56.54541850090027,
    "box_points": [
      137,
      104,
      161,
      129
    ]
  },
  "735-683-N--2020-05-05--13.10.23--detections--8--car--71.5--19x18--161.102v180.120": {
    "type": "car",
    "id": "735-683-N--2020-05-05--13.10.23--detections--8--car--71.5--19x18--161.102v180.120",
    "percentage_probability": 71.52113914489746,
    "box_points": [
      161,
      102,
      180,
      120
    ]
  },
  "735-683-N--2020-05-05--13.10.23--detections--9--bus--32.2--24x25--137.104v161.129": {
    "type": "bus",
    "id": "735-683-N--2020-05-05--13.10.23--detections--9--bus--32.2--24x25--137.104v161.129",
    "percentage_probability": 32.239919900894165,
    "box_points": [
      137,
      104,
      161,
      129
    ]
  },
  "735-683-N--2020-05-05--13.10.23--detections--10--car--63.8--44x42--169.122v213.164": {
    "type": "car",
    "id": "735-683-N--2020-05-05--13.10.23--detections--10--car--63.8--44x42--169.122v213.164",
    "percentage_probability": 63.773804903030396,
    "box_points": [
      169,
      122,
      213,
      164
    ]
  },
  "735-683-N--2020-05-05--13.10.23--detections--11--car--77.0--49x45--129.140v178.185": {
    "type": "car",
    "id": "735-683-N--2020-05-05--13.10.23--detections--11--car--77.0--49x45--129.140v178.185",
    "percentage_probability": 77.03096866607666,
    "box_points": [
      129,
      140,
      178,
      185
    ]
  },
  "735-683-N--2020-05-05--13.10.23--detections--12--car--60.1--55x55--283.136v338.191": {
    "type": "car",
    "id": "735-683-N--2020-05-05--13.10.23--detections--12--car--60.1--55x55--283.136v338.191",
    "percentage_probability": 60.088735818862915,
    "box_points": [
      283,
      136,
      338,
      191
    ]
  }
}
