{
  "id": "735-683-N--2020-05-05--13.49.12--detections",
  "model": "ResNet50_COCO_best_v2.0.1.h5",
  "summary": {
    "total": 11,
    "car": 11
  },
  "735-683-N--2020-05-05--13.49.12--detections--1--car--32.5--11x10--132.84v143.94": {
    "type": "car",
    "id": "735-683-N--2020-05-05--13.49.12--detections--1--car--32.5--11x10--132.84v143.94",
    "percentage_probability": 32.48291611671448,
    "box_points": [
      132,
      84,
      143,
      94
    ]
  },
  "735-683-N--2020-05-05--13.49.12--detections--2--car--31.7--11x7--207.86v218.93": {
    "type": "car",
    "id": "735-683-N--2020-05-05--13.49.12--detections--2--car--31.7--11x7--207.86v218.93",
    "percentage_probability": 31.6622257232666,
    "box_points": [
      207,
      86,
      218,
      93
    ]
  },
  "735-683-N--2020-05-05--13.49.12--detections--3--car--48.0--10x10--119.86v129.96": {
    "type": "car",
    "id": "735-683-N--2020-05-05--13.49.12--detections--3--car--48.0--10x10--119.86v129.96",
    "percentage_probability": 48.03379774093628,
    "box_points": [
      119,
      86,
      129,
      96
    ]
  },
  "735-683-N--2020-05-05--13.49.12--detections--4--car--47.0--12x13--141.87v153.100": {
    "type": "car",
    "id": "735-683-N--2020-05-05--13.49.12--detections--4--car--47.0--12x13--141.87v153.100",
    "percentage_probability": 47.033026814460754,
    "box_points": [
      141,
      87,
      153,
      100
    ]
  },
  "735-683-N--2020-05-05--13.49.12--detections--5--car--70.9--18x13--162.99v180.112": {
    "type": "car",
    "id": "735-683-N--2020-05-05--13.49.12--detections--5--car--70.9--18x13--162.99v180.112",
    "percentage_probability": 70.89390754699707,
    "box_points": [
      162,
      99,
      180,
      112
    ]
  },
  "735-683-N--2020-05-05--13.49.12--detections--6--car--36.4--21x17--106.111v127.128": {
    "type": "car",
    "id": "735-683-N--2020-05-05--13.49.12--detections--6--car--36.4--21x17--106.111v127.128",
    "percentage_probability": 36.43641471862793,
    "box_points": [
      106,
      111,
      127,
      128
    ]
  },
  "735-683-N--2020-05-05--13.49.12--detections--7--car--32.9--15x17--114.79v129.96": {
    "type": "car",
    "id": "735-683-N--2020-05-05--13.49.12--detections--7--car--32.9--15x17--114.79v129.96",
    "percentage_probability": 32.90388584136963,
    "box_points": [
      114,
      79,
      129,
      96
    ]
  },
  "735-683-N--2020-05-05--13.49.12--detections--8--car--76.2--21x25--0.103v21.128": {
    "type": "car",
    "id": "735-683-N--2020-05-05--13.49.12--detections--8--car--76.2--21x25--0.103v21.128",
    "percentage_probability": 76.24990940093994,
    "box_points": [
      0,
      103,
      21,
      128
    ]
  },
  "735-683-N--2020-05-05--13.49.12--detections--9--car--82.5--24x23--150.111v174.134": {
    "type": "car",
    "id": "735-683-N--2020-05-05--13.49.12--detections--9--car--82.5--24x23--150.111v174.134",
    "percentage_probability": 82.53527283668518,
    "box_points": [
      150,
      111,
      174,
      134
    ]
  },
  "735-683-N--2020-05-05--13.49.12--detections--10--car--78.9--37x37--169.119v206.156": {
    "type": "car",
    "id": "735-683-N--2020-05-05--13.49.12--detections--10--car--78.9--37x37--169.119v206.156",
    "percentage_probability": 78.91160249710083,
    "box_points": [
      169,
      119,
      206,
      156
    ]
  },
  "735-683-N--2020-05-05--13.49.12--detections--11--car--95.7--61x60--142.160v203.220": {
    "type": "car",
    "id": "735-683-N--2020-05-05--13.49.12--detections--11--car--95.7--61x60--142.160v203.220",
    "percentage_probability": 95.70006132125854,
    "box_points": [
      142,
      160,
      203,
      220
    ]
  }
}
