{
  "id": "735-683-N--2020-05-05--13.26.02--detections",
  "model": "ResNet50_COCO_best_v2.0.1.h5",
  "summary": {
    "total": 13,
    "car": 12,
    "bus": 1
  },
  "735-683-N--2020-05-05--13.26.02--detections--1--car--35.7--13x11--175.82v188.93": {
    "type": "car",
    "id": "735-683-N--2020-05-05--13.26.02--detections--1--car--35.7--13x11--175.82v188.93",
    "percentage_probability": 35.72489619255066,
    "box_points": [
      175,
      82,
      188,
      93
    ]
  },
  "735-683-N--2020-05-05--13.26.02--detections--2--car--61.6--11x8--191.83v202.91": {
    "type": "car",
    "id": "735-683-N--2020-05-05--13.26.02--detections--2--car--61.6--11x8--191.83v202.91",
    "percentage_probability": 61.577218770980835,
    "box_points": [
      191,
      83,
      202,
      91
    ]
  },
  "735-683-N--2020-05-05--13.26.02--detections--3--car--27.4--12x11--118.91v130.102": {
    "type": "car",
    "id": "735-683-N--2020-05-05--13.26.02--detections--3--car--27.4--12x11--118.91v130.102",
    "percentage_probability": 27.392899990081787,
    "box_points": [
      118,
      91,
      130,
      102
    ]
  },
  "735-683-N--2020-05-05--13.26.02--detections--4--car--26.5--11x11--141.91v152.102": {
    "type": "car",
    "id": "735-683-N--2020-05-05--13.26.02--detections--4--car--26.5--11x11--141.91v152.102",
    "percentage_probability": 26.490163803100586,
    "box_points": [
      141,
      91,
      152,
      102
    ]
  },
  "735-683-N--2020-05-05--13.26.02--detections--5--car--29.3--9x12--142.96v151.108": {
    "type": "car",
    "id": "735-683-N--2020-05-05--13.26.02--detections--5--car--29.3--9x12--142.96v151.108",
    "percentage_probability": 29.31950092315674,
    "box_points": [
      142,
      96,
      151,
      108
    ]
  },
  "735-683-N--2020-05-05--13.26.02--detections--6--car--25.2--18x14--174.78v192.92": {
    "type": "car",
    "id": "735-683-N--2020-05-05--13.26.02--detections--6--car--25.2--18x14--174.78v192.92",
    "percentage_probability": 25.194698572158813,
    "box_points": [
      174,
      78,
      192,
      92
    ]
  },
  "735-683-N--2020-05-05--13.26.02--detections--7--bus--31.9--18x20--54.98v72.118": {
    "type": "bus",
    "id": "735-683-N--2020-05-05--13.26.02--detections--7--bus--31.9--18x20--54.98v72.118",
    "percentage_probability": 31.94338083267212,
    "box_points": [
      54,
      98,
      72,
      118
    ]
  },
  "735-683-N--2020-05-05--13.26.02--detections--8--car--39.3--21x21--153.100v174.121": {
    "type": "car",
    "id": "735-683-N--2020-05-05--13.26.02--detections--8--car--39.3--21x21--153.100v174.121",
    "percentage_probability": 39.3421471118927,
    "box_points": [
      153,
      100,
      174,
      121
    ]
  },
  "735-683-N--2020-05-05--13.26.02--detections--9--car--41.0--18x19--54.99v72.118": {
    "type": "car",
    "id": "735-683-N--2020-05-05--13.26.02--detections--9--car--41.0--18x19--54.99v72.118",
    "percentage_probability": 41.0100519657135,
    "box_points": [
      54,
      99,
      72,
      118
    ]
  },
  "735-683-N--2020-05-05--13.26.02--detections--10--car--48.8--26x20--182.113v208.133": {
    "type": "car",
    "id": "735-683-N--2020-05-05--13.26.02--detections--10--car--48.8--26x20--182.113v208.133",
    "percentage_probability": 48.812368512153625,
    "box_points": [
      182,
      113,
      208,
      133
    ]
  },
  "735-683-N--2020-05-05--13.26.02--detections--11--car--31.7--26x20--184.120v210.140": {
    "type": "car",
    "id": "735-683-N--2020-05-05--13.26.02--detections--11--car--31.7--26x20--184.120v210.140",
    "percentage_probability": 31.688061356544495,
    "box_points": [
      184,
      120,
      210,
      140
    ]
  },
  "735-683-N--2020-05-05--13.26.02--detections--12--car--76.9--45x46--182.125v227.171": {
    "type": "car",
    "id": "735-683-N--2020-05-05--13.26.02--detections--12--car--76.9--45x46--182.125v227.171",
    "percentage_probability": 76.86102390289307,
    "box_points": [
      182,
      125,
      227,
      171
    ]
  },
  "735-683-N--2020-05-05--13.26.02--detections--13--car--96.3--70x66--142.168v212.234": {
    "type": "car",
    "id": "735-683-N--2020-05-05--13.26.02--detections--13--car--96.3--70x66--142.168v212.234",
    "percentage_probability": 96.2625503540039,
    "box_points": [
      142,
      168,
      212,
      234
    ]
  }
}
