{
  "id": "735-683-N--2020-05-05--13.43.59--detections",
  "model": "ResNet50_COCO_best_v2.0.1.h5",
  "summary": {
    "total": 4,
    "car": 4
  },
  "735-683-N--2020-05-05--13.43.59--detections--1--car--33.6--9x7--151.81v160.88": {
    "type": "car",
    "id": "735-683-N--2020-05-05--13.43.59--detections--1--car--33.6--9x7--151.81v160.88",
    "percentage_probability": 33.64802896976471,
    "box_points": [
      151,
      81,
      160,
      88
    ]
  },
  "735-683-N--2020-05-05--13.43.59--detections--2--car--47.6--12x11--124.90v136.101": {
    "type": "car",
    "id": "735-683-N--2020-05-05--13.43.59--detections--2--car--47.6--12x11--124.90v136.101",
    "percentage_probability": 47.6081520318985,
    "box_points": [
      124,
      90,
      136,
      101
    ]
  },
  "735-683-N--2020-05-05--13.43.59--detections--3--car--82.2--20x24--0.103v20.127": {
    "type": "car",
    "id": "735-683-N--2020-05-05--13.43.59--detections--3--car--82.2--20x24--0.103v20.127",
    "percentage_probability": 82.16979503631592,
    "box_points": [
      0,
      103,
      20,
      127
    ]
  },
  "735-683-N--2020-05-05--13.43.59--detections--4--car--68.6--23x20--132.105v155.125": {
    "type": "car",
    "id": "735-683-N--2020-05-05--13.43.59--detections--4--car--68.6--23x20--132.105v155.125",
    "percentage_probability": 68.6325192451477,
    "box_points": [
      132,
      105,
      155,
      125
    ]
  }
}
