{
  "id": "735-683-N--2020-05-05--13.44.30--detections",
  "model": "ResNet50_COCO_best_v2.0.1.h5",
  "summary": {
    "total": 14,
    "car": 13,
    "bus": 1
  },
  "735-683-N--2020-05-05--13.44.30--detections--1--car--41.9--10x8--171.82v181.90": {
    "type": "car",
    "id": "735-683-N--2020-05-05--13.44.30--detections--1--car--41.9--10x8--171.82v181.90",
    "percentage_probability": 41.857606172561646,
    "box_points": [
      171,
      82,
      181,
      90
    ]
  },
  "735-683-N--2020-05-05--13.44.30--detections--2--car--25.1--14x15--122.87v136.102": {
    "type": "car",
    "id": "735-683-N--2020-05-05--13.44.30--detections--2--car--25.1--14x15--122.87v136.102",
    "percentage_probability": 25.138118863105774,
    "box_points": [
      122,
      87,
      136,
      102
    ]
  },
  "735-683-N--2020-05-05--13.44.30--detections--3--car--30.3--9x13--137.89v146.102": {
    "type": "car",
    "id": "735-683-N--2020-05-05--13.44.30--detections--3--car--30.3--9x13--137.89v146.102",
    "percentage_probability": 30.330586433410645,
    "box_points": [
      137,
      89,
      146,
      102
    ]
  },
  "735-683-N--2020-05-05--13.44.30--detections--4--car--43.2--15x15--144.90v159.105": {
    "type": "car",
    "id": "735-683-N--2020-05-05--13.44.30--detections--4--car--43.2--15x15--144.90v159.105",
    "percentage_probability": 43.228524923324585,
    "box_points": [
      144,
      90,
      159,
      105
    ]
  },
  "735-683-N--2020-05-05--13.44.30--detections--5--car--69.8--15x14--126.99v141.113": {
    "type": "car",
    "id": "735-683-N--2020-05-05--13.44.30--detections--5--car--69.8--15x14--126.99v141.113",
    "percentage_probability": 69.82915997505188,
    "box_points": [
      126,
      99,
      141,
      113
    ]
  },
  "735-683-N--2020-05-05--13.44.30--detections--6--car--28.6--17x11--160.104v177.115": {
    "type": "car",
    "id": "735-683-N--2020-05-05--13.44.30--detections--6--car--28.6--17x11--160.104v177.115",
    "percentage_probability": 28.554728627204895,
    "box_points": [
      160,
      104,
      177,
      115
    ]
  },
  "735-683-N--2020-05-05--13.44.30--detections--7--car--72.1--21x18--158.105v179.123": {
    "type": "car",
    "id": "735-683-N--2020-05-05--13.44.30--detections--7--car--72.1--21x18--158.105v179.123",
    "percentage_probability": 72.14382886886597,
    "box_points": [
      158,
      105,
      179,
      123
    ]
  },
  "735-683-N--2020-05-05--13.44.30--detections--8--car--63.5--25x26--135.104v160.130": {
    "type": "car",
    "id": "735-683-N--2020-05-05--13.44.30--detections--8--car--63.5--25x26--135.104v160.130",
    "percentage_probability": 63.45200538635254,
    "box_points": [
      135,
      104,
      160,
      130
    ]
  },
  "735-683-N--2020-05-05--13.44.30--detections--9--bus--27.4--25x25--135.105v160.130": {
    "type": "bus",
    "id": "735-683-N--2020-05-05--13.44.30--detections--9--bus--27.4--25x25--135.105v160.130",
    "percentage_probability": 27.361726760864258,
    "box_points": [
      135,
      105,
      160,
      130
    ]
  },
  "735-683-N--2020-05-05--13.44.30--detections--10--car--89.3--34x32--183.105v217.137": {
    "type": "car",
    "id": "735-683-N--2020-05-05--13.44.30--detections--10--car--89.3--34x32--183.105v217.137",
    "percentage_probability": 89.25479650497437,
    "box_points": [
      183,
      105,
      217,
      137
    ]
  },
  "735-683-N--2020-05-05--13.44.30--detections--11--car--86.6--53x45--122.140v175.185": {
    "type": "car",
    "id": "735-683-N--2020-05-05--13.44.30--detections--11--car--86.6--53x45--122.140v175.185",
    "percentage_probability": 86.57989501953125,
    "box_points": [
      122,
      140,
      175,
      185
    ]
  },
  "735-683-N--2020-05-05--13.44.30--detections--12--car--73.5--91x68--235.145v326.213": {
    "type": "car",
    "id": "735-683-N--2020-05-05--13.44.30--detections--12--car--73.5--91x68--235.145v326.213",
    "percentage_probability": 73.49616885185242,
    "box_points": [
      235,
      145,
      326,
      213
    ]
  },
  "735-683-N--2020-05-05--13.44.30--detections--13--car--66.6--29x62--321.154v350.216": {
    "type": "car",
    "id": "735-683-N--2020-05-05--13.44.30--detections--13--car--66.6--29x62--321.154v350.216",
    "percentage_probability": 66.57578945159912,
    "box_points": [
      321,
      154,
      350,
      216
    ]
  },
  "735-683-N--2020-05-05--13.44.30--detections--14--car--65.2--102x29--217.208v319.237": {
    "type": "car",
    "id": "735-683-N--2020-05-05--13.44.30--detections--14--car--65.2--102x29--217.208v319.237",
    "percentage_probability": 65.2421236038208,
    "box_points": [
      217,
      208,
      319,
      237
    ]
  }
}
