{
  "id": "735-683-N--2020-05-05--13.28.08--detections",
  "model": "ResNet50_COCO_best_v2.0.1.h5",
  "summary": {
    "total": 8,
    "car": 8
  },
  "735-683-N--2020-05-05--13.28.08--detections--1--car--38.7--11x12--119.79v130.91": {
    "type": "car",
    "id": "735-683-N--2020-05-05--13.28.08--detections--1--car--38.7--11x12--119.79v130.91",
    "percentage_probability": 38.709354400634766,
    "box_points": [
      119,
      79,
      130,
      91
    ]
  },
  "735-683-N--2020-05-05--13.28.08--detections--2--car--31.9--11x9--119.87v130.96": {
    "type": "car",
    "id": "735-683-N--2020-05-05--13.28.08--detections--2--car--31.9--11x9--119.87v130.96",
    "percentage_probability": 31.90951943397522,
    "box_points": [
      119,
      87,
      130,
      96
    ]
  },
  "735-683-N--2020-05-05--13.28.08--detections--3--car--34.4--11x11--121.89v132.100": {
    "type": "car",
    "id": "735-683-N--2020-05-05--13.28.08--detections--3--car--34.4--11x11--121.89v132.100",
    "percentage_probability": 34.4163715839386,
    "box_points": [
      121,
      89,
      132,
      100
    ]
  },
  "735-683-N--2020-05-05--13.28.08--detections--4--car--55.3--12x14--122.91v134.105": {
    "type": "car",
    "id": "735-683-N--2020-05-05--13.28.08--detections--4--car--55.3--12x14--122.91v134.105",
    "percentage_probability": 55.32798171043396,
    "box_points": [
      122,
      91,
      134,
      105
    ]
  },
  "735-683-N--2020-05-05--13.28.08--detections--5--car--53.3--18x20--131.97v149.117": {
    "type": "car",
    "id": "735-683-N--2020-05-05--13.28.08--detections--5--car--53.3--18x20--131.97v149.117",
    "percentage_probability": 53.288304805755615,
    "box_points": [
      131,
      97,
      149,
      117
    ]
  },
  "735-683-N--2020-05-05--13.28.08--detections--6--car--28.9--14x17--119.81v133.98": {
    "type": "car",
    "id": "735-683-N--2020-05-05--13.28.08--detections--6--car--28.9--14x17--119.81v133.98",
    "percentage_probability": 28.917789459228516,
    "box_points": [
      119,
      81,
      133,
      98
    ]
  },
  "735-683-N--2020-05-05--13.28.08--detections--7--car--33.5--17x19--147.93v164.112": {
    "type": "car",
    "id": "735-683-N--2020-05-05--13.28.08--detections--7--car--33.5--17x19--147.93v164.112",
    "percentage_probability": 33.52733254432678,
    "box_points": [
      147,
      93,
      164,
      112
    ]
  },
  "735-683-N--2020-05-05--13.28.08--detections--8--car--95.7--34x32--195.112v229.144": {
    "type": "car",
    "id": "735-683-N--2020-05-05--13.28.08--detections--8--car--95.7--34x32--195.112v229.144",
    "percentage_probability": 95.67337036132812,
    "box_points": [
      195,
      112,
      229,
      144
    ]
  }
}
