{
  "id": "735-683-N--2020-05-05--13.30.07--detections",
  "model": "ResNet50_COCO_best_v2.0.1.h5",
  "summary": {
    "total": 10,
    "car": 9,
    "bus": 1
  },
  "735-683-N--2020-05-05--13.30.07--detections--1--car--27.9--10x9--115.80v125.89": {
    "type": "car",
    "id": "735-683-N--2020-05-05--13.30.07--detections--1--car--27.9--10x9--115.80v125.89",
    "percentage_probability": 27.906396985054016,
    "box_points": [
      115,
      80,
      125,
      89
    ]
  },
  "735-683-N--2020-05-05--13.30.07--detections--2--car--26.3--12x10--115.85v127.95": {
    "type": "car",
    "id": "735-683-N--2020-05-05--13.30.07--detections--2--car--26.3--12x10--115.85v127.95",
    "percentage_probability": 26.343801617622375,
    "box_points": [
      115,
      85,
      127,
      95
    ]
  },
  "735-683-N--2020-05-05--13.30.07--detections--3--car--34.6--12x10--131.83v143.93": {
    "type": "car",
    "id": "735-683-N--2020-05-05--13.30.07--detections--3--car--34.6--12x10--131.83v143.93",
    "percentage_probability": 34.60513651371002,
    "box_points": [
      131,
      83,
      143,
      93
    ]
  },
  "735-683-N--2020-05-05--13.30.07--detections--4--car--43.3--13x10--117.88v130.98": {
    "type": "car",
    "id": "735-683-N--2020-05-05--13.30.07--detections--4--car--43.3--13x10--117.88v130.98",
    "percentage_probability": 43.255746364593506,
    "box_points": [
      117,
      88,
      130,
      98
    ]
  },
  "735-683-N--2020-05-05--13.30.07--detections--5--car--74.9--15x15--125.97v140.112": {
    "type": "car",
    "id": "735-683-N--2020-05-05--13.30.07--detections--5--car--74.9--15x15--125.97v140.112",
    "percentage_probability": 74.86337423324585,
    "box_points": [
      125,
      97,
      140,
      112
    ]
  },
  "735-683-N--2020-05-05--13.30.07--detections--6--car--71.0--25x22--137.109v162.131": {
    "type": "car",
    "id": "735-683-N--2020-05-05--13.30.07--detections--6--car--71.0--25x22--137.109v162.131",
    "percentage_probability": 71.02397680282593,
    "box_points": [
      137,
      109,
      162,
      131
    ]
  },
  "735-683-N--2020-05-05--13.30.07--detections--7--car--86.7--29x28--180.107v209.135": {
    "type": "car",
    "id": "735-683-N--2020-05-05--13.30.07--detections--7--car--86.7--29x28--180.107v209.135",
    "percentage_probability": 86.67293190956116,
    "box_points": [
      180,
      107,
      209,
      135
    ]
  },
  "735-683-N--2020-05-05--13.30.07--detections--8--car--93.0--77x68--230.148v307.216": {
    "type": "car",
    "id": "735-683-N--2020-05-05--13.30.07--detections--8--car--93.0--77x68--230.148v307.216",
    "percentage_probability": 92.99023747444153,
    "box_points": [
      230,
      148,
      307,
      216
    ]
  },
  "735-683-N--2020-05-05--13.30.07--detections--9--bus--29.5--85x74--148.163v233.237": {
    "type": "bus",
    "id": "735-683-N--2020-05-05--13.30.07--detections--9--bus--29.5--85x74--148.163v233.237",
    "percentage_probability": 29.468563199043274,
    "box_points": [
      148,
      163,
      233,
      237
    ]
  },
  "735-683-N--2020-05-05--13.30.07--detections--10--car--78.1--88x74--148.163v236.237": {
    "type": "car",
    "id": "735-683-N--2020-05-05--13.30.07--detections--10--car--78.1--88x74--148.163v236.237",
    "percentage_probability": 78.09959650039673,
    "box_points": [
      148,
      163,
      236,
      237
    ]
  }
}
