{
  "id": "735-683-N--2020-05-05--13.51.11--detections",
  "model": "ResNet50_COCO_best_v2.0.1.h5",
  "summary": {
    "total": 11,
    "car": 11
  },
  "735-683-N--2020-05-05--13.51.11--detections--1--car--25.4--9x8--123.75v132.83": {
    "type": "car",
    "id": "735-683-N--2020-05-05--13.51.11--detections--1--car--25.4--9x8--123.75v132.83",
    "percentage_probability": 25.44255256652832,
    "box_points": [
      123,
      75,
      132,
      83
    ]
  },
  "735-683-N--2020-05-05--13.51.11--detections--2--car--31.2--9x9--163.80v172.89": {
    "type": "car",
    "id": "735-683-N--2020-05-05--13.51.11--detections--2--car--31.2--9x9--163.80v172.89",
    "percentage_probability": 31.220662593841553,
    "box_points": [
      163,
      80,
      172,
      89
    ]
  },
  "735-683-N--2020-05-05--13.51.11--detections--3--car--28.3--7x8--184.82v191.90": {
    "type": "car",
    "id": "735-683-N--2020-05-05--13.51.11--detections--3--car--28.3--7x8--184.82v191.90",
    "percentage_probability": 28.299802541732788,
    "box_points": [
      184,
      82,
      191,
      90
    ]
  },
  "735-683-N--2020-05-05--13.51.11--detections--4--car--27.6--17x10--131.100v148.110": {
    "type": "car",
    "id": "735-683-N--2020-05-05--13.51.11--detections--4--car--27.6--17x10--131.100v148.110",
    "percentage_probability": 27.61986255645752,
    "box_points": [
      131,
      100,
      148,
      110
    ]
  },
  "735-683-N--2020-05-05--13.51.11--detections--5--car--56.1--19x18--130.100v149.118": {
    "type": "car",
    "id": "735-683-N--2020-05-05--13.51.11--detections--5--car--56.1--19x18--130.100v149.118",
    "percentage_probability": 56.09357953071594,
    "box_points": [
      130,
      100,
      149,
      118
    ]
  },
  "735-683-N--2020-05-05--13.51.11--detections--6--car--89.6--23x22--167.103v190.125": {
    "type": "car",
    "id": "735-683-N--2020-05-05--13.51.11--detections--6--car--89.6--23x22--167.103v190.125",
    "percentage_probability": 89.5901083946228,
    "box_points": [
      167,
      103,
      190,
      125
    ]
  },
  "735-683-N--2020-05-05--13.51.11--detections--7--car--75.0--29x27--106.112v135.139": {
    "type": "car",
    "id": "735-683-N--2020-05-05--13.51.11--detections--7--car--75.0--29x27--106.112v135.139",
    "percentage_probability": 75.04786252975464,
    "box_points": [
      106,
      112,
      135,
      139
    ]
  },
  "735-683-N--2020-05-05--13.51.11--detections--8--car--65.6--40x40--220.120v260.160": {
    "type": "car",
    "id": "735-683-N--2020-05-05--13.51.11--detections--8--car--65.6--40x40--220.120v260.160",
    "percentage_probability": 65.63259363174438,
    "box_points": [
      220,
      120,
      260,
      160
    ]
  },
  "735-683-N--2020-05-05--13.51.11--detections--9--car--44.5--56x39--292.138v348.177": {
    "type": "car",
    "id": "735-683-N--2020-05-05--13.51.11--detections--9--car--44.5--56x39--292.138v348.177",
    "percentage_probability": 44.523051381111145,
    "box_points": [
      292,
      138,
      348,
      177
    ]
  },
  "735-683-N--2020-05-05--13.51.11--detections--10--car--94.5--58x46--200.147v258.193": {
    "type": "car",
    "id": "735-683-N--2020-05-05--13.51.11--detections--10--car--94.5--58x46--200.147v258.193",
    "percentage_probability": 94.53932046890259,
    "box_points": [
      200,
      147,
      258,
      193
    ]
  },
  "735-683-N--2020-05-05--13.51.11--detections--11--car--47.9--70x65--287.173v357.238": {
    "type": "car",
    "id": "735-683-N--2020-05-05--13.51.11--detections--11--car--47.9--70x65--287.173v357.238",
    "percentage_probability": 47.90915250778198,
    "box_points": [
      287,
      173,
      357,
      238
    ]
  }
}
