{
  "id": "735-683-N--2020-05-05--13.10.15--detections",
  "model": "ResNet50_COCO_best_v2.0.1.h5",
  "summary": {
    "total": 7,
    "car": 6,
    "bus": 1
  },
  "735-683-N--2020-05-05--13.10.15--detections--1--car--39.1--15x15--123.91v138.106": {
    "type": "car",
    "id": "735-683-N--2020-05-05--13.10.15--detections--1--car--39.1--15x15--123.91v138.106",
    "percentage_probability": 39.09330070018768,
    "box_points": [
      123,
      91,
      138,
      106
    ]
  },
  "735-683-N--2020-05-05--13.10.15--detections--2--car--65.8--17x12--59.101v76.113": {
    "type": "car",
    "id": "735-683-N--2020-05-05--13.10.15--detections--2--car--65.8--17x12--59.101v76.113",
    "percentage_probability": 65.76573848724365,
    "box_points": [
      59,
      101,
      76,
      113
    ]
  },
  "735-683-N--2020-05-05--13.10.15--detections--3--car--28.7--9x10--150.100v159.110": {
    "type": "car",
    "id": "735-683-N--2020-05-05--13.10.15--detections--3--car--28.7--9x10--150.100v159.110",
    "percentage_probability": 28.699928522109985,
    "box_points": [
      150,
      100,
      159,
      110
    ]
  },
  "735-683-N--2020-05-05--13.10.15--detections--4--car--60.5--29x25--108.113v137.138": {
    "type": "car",
    "id": "735-683-N--2020-05-05--13.10.15--detections--4--car--60.5--29x25--108.113v137.138",
    "percentage_probability": 60.515791177749634,
    "box_points": [
      108,
      113,
      137,
      138
    ]
  },
  "735-683-N--2020-05-05--13.10.15--detections--5--car--35.2--17x53--334.165v351.218": {
    "type": "car",
    "id": "735-683-N--2020-05-05--13.10.15--detections--5--car--35.2--17x53--334.165v351.218",
    "percentage_probability": 35.20921468734741,
    "box_points": [
      334,
      165,
      351,
      218
    ]
  },
  "735-683-N--2020-05-05--13.10.15--detections--6--bus--56.7--46x64--168.98v214.162": {
    "type": "bus",
    "id": "735-683-N--2020-05-05--13.10.15--detections--6--bus--56.7--46x64--168.98v214.162",
    "percentage_probability": 56.68046474456787,
    "box_points": [
      168,
      98,
      214,
      162
    ]
  },
  "735-683-N--2020-05-05--13.10.15--detections--7--car--80.8--34x55--317.160v351.215": {
    "type": "car",
    "id": "735-683-N--2020-05-05--13.10.15--detections--7--car--80.8--34x55--317.160v351.215",
    "percentage_probability": 80.78300356864929,
    "box_points": [
      317,
      160,
      351,
      215
    ]
  }
}
