{
  "id": "735-683-N--2020-05-05--13.37.24--detections",
  "model": "ResNet50_COCO_best_v2.0.1.h5",
  "summary": {
    "total": 10,
    "car": 9,
    "bus": 1
  },
  "735-683-N--2020-05-05--13.37.24--detections--1--car--33.5--10x12--117.80v127.92": {
    "type": "car",
    "id": "735-683-N--2020-05-05--13.37.24--detections--1--car--33.5--10x12--117.80v127.92",
    "percentage_probability": 33.51069092750549,
    "box_points": [
      117,
      80,
      127,
      92
    ]
  },
  "735-683-N--2020-05-05--13.37.24--detections--2--car--56.3--10x7--162.82v172.89": {
    "type": "car",
    "id": "735-683-N--2020-05-05--13.37.24--detections--2--car--56.3--10x7--162.82v172.89",
    "percentage_probability": 56.277620792388916,
    "box_points": [
      162,
      82,
      172,
      89
    ]
  },
  "735-683-N--2020-05-05--13.37.24--detections--3--car--52.4--11x11--196.84v207.95": {
    "type": "car",
    "id": "735-683-N--2020-05-05--13.37.24--detections--3--car--52.4--11x11--196.84v207.95",
    "percentage_probability": 52.41312384605408,
    "box_points": [
      196,
      84,
      207,
      95
    ]
  },
  "735-683-N--2020-05-05--13.37.24--detections--4--bus--25.3--13x17--135.80v148.97": {
    "type": "bus",
    "id": "735-683-N--2020-05-05--13.37.24--detections--4--bus--25.3--13x17--135.80v148.97",
    "percentage_probability": 25.302058458328247,
    "box_points": [
      135,
      80,
      148,
      97
    ]
  },
  "735-683-N--2020-05-05--13.37.24--detections--5--car--33.1--12x13--124.90v136.103": {
    "type": "car",
    "id": "735-683-N--2020-05-05--13.37.24--detections--5--car--33.1--12x13--124.90v136.103",
    "percentage_probability": 33.118534088134766,
    "box_points": [
      124,
      90,
      136,
      103
    ]
  },
  "735-683-N--2020-05-05--13.37.24--detections--6--car--63.0--15x22--122.91v137.113": {
    "type": "car",
    "id": "735-683-N--2020-05-05--13.37.24--detections--6--car--63.0--15x22--122.91v137.113",
    "percentage_probability": 62.958383560180664,
    "box_points": [
      122,
      91,
      137,
      113
    ]
  },
  "735-683-N--2020-05-05--13.37.24--detections--7--car--35.0--14x16--134.81v148.97": {
    "type": "car",
    "id": "735-683-N--2020-05-05--13.37.24--detections--7--car--35.0--14x16--134.81v148.97",
    "percentage_probability": 35.042643547058105,
    "box_points": [
      134,
      81,
      148,
      97
    ]
  },
  "735-683-N--2020-05-05--13.37.24--detections--8--car--75.6--30x27--137.103v167.130": {
    "type": "car",
    "id": "735-683-N--2020-05-05--13.37.24--detections--8--car--75.6--30x27--137.103v167.130",
    "percentage_probability": 75.6054162979126,
    "box_points": [
      137,
      103,
      167,
      130
    ]
  },
  "735-683-N--2020-05-05--13.37.24--detections--9--car--85.1--40x86--312.134v352.220": {
    "type": "car",
    "id": "735-683-N--2020-05-05--13.37.24--detections--9--car--85.1--40x86--312.134v352.220",
    "percentage_probability": 85.11948585510254,
    "box_points": [
      312,
      134,
      352,
      220
    ]
  },
  "735-683-N--2020-05-05--13.37.24--detections--10--car--96.4--70x80--143.143v213.223": {
    "type": "car",
    "id": "735-683-N--2020-05-05--13.37.24--detections--10--car--96.4--70x80--143.143v213.223",
    "percentage_probability": 96.38410210609436,
    "box_points": [
      143,
      143,
      213,
      223
    ]
  }
}
