{
  "id": "735-683-N--2020-05-05--13.30.41--detections",
  "model": "ResNet50_COCO_best_v2.0.1.h5",
  "summary": {
    "total": 6,
    "car": 6
  },
  "735-683-N--2020-05-05--13.30.41--detections--1--car--30.8--10x10--112.80v122.90": {
    "type": "car",
    "id": "735-683-N--2020-05-05--13.30.41--detections--1--car--30.8--10x10--112.80v122.90",
    "percentage_probability": 30.836084485054016,
    "box_points": [
      112,
      80,
      122,
      90
    ]
  },
  "735-683-N--2020-05-05--13.30.41--detections--2--car--32.6--14x17--119.84v133.101": {
    "type": "car",
    "id": "735-683-N--2020-05-05--13.30.41--detections--2--car--32.6--14x17--119.84v133.101",
    "percentage_probability": 32.64148831367493,
    "box_points": [
      119,
      84,
      133,
      101
    ]
  },
  "735-683-N--2020-05-05--13.30.41--detections--3--car--39.4--24x16--107.106v131.122": {
    "type": "car",
    "id": "735-683-N--2020-05-05--13.30.41--detections--3--car--39.4--24x16--107.106v131.122",
    "percentage_probability": 39.363548159599304,
    "box_points": [
      107,
      106,
      131,
      122
    ]
  },
  "735-683-N--2020-05-05--13.30.41--detections--4--car--54.8--27x27--105.106v132.133": {
    "type": "car",
    "id": "735-683-N--2020-05-05--13.30.41--detections--4--car--54.8--27x27--105.106v132.133",
    "percentage_probability": 54.79761362075806,
    "box_points": [
      105,
      106,
      132,
      133
    ]
  },
  "735-683-N--2020-05-05--13.30.41--detections--5--car--86.7--31x27--153.117v184.144": {
    "type": "car",
    "id": "735-683-N--2020-05-05--13.30.41--detections--5--car--86.7--31x27--153.117v184.144",
    "percentage_probability": 86.71881556510925,
    "box_points": [
      153,
      117,
      184,
      144
    ]
  },
  "735-683-N--2020-05-05--13.30.41--detections--6--car--59.8--49x45--236.122v285.167": {
    "type": "car",
    "id": "735-683-N--2020-05-05--13.30.41--detections--6--car--59.8--49x45--236.122v285.167",
    "percentage_probability": 59.84330773353577,
    "box_points": [
      236,
      122,
      285,
      167
    ]
  }
}
