{
  "id": "735-683-N--2020-05-05--13.29.20--detections",
  "model": "ResNet50_COCO_best_v2.0.1.h5",
  "summary": {
    "total": 10,
    "car": 9,
    "bus": 1
  },
  "735-683-N--2020-05-05--13.29.20--detections--1--car--31.9--8x7--112.80v120.87": {
    "type": "car",
    "id": "735-683-N--2020-05-05--13.29.20--detections--1--car--31.9--8x7--112.80v120.87",
    "percentage_probability": 31.894466280937195,
    "box_points": [
      112,
      80,
      120,
      87
    ]
  },
  "735-683-N--2020-05-05--13.29.20--detections--2--car--28.0--13x8--160.82v173.90": {
    "type": "car",
    "id": "735-683-N--2020-05-05--13.29.20--detections--2--car--28.0--13x8--160.82v173.90",
    "percentage_probability": 28.02606225013733,
    "box_points": [
      160,
      82,
      173,
      90
    ]
  },
  "735-683-N--2020-05-05--13.29.20--detections--3--car--33.5--9x9--129.85v138.94": {
    "type": "car",
    "id": "735-683-N--2020-05-05--13.29.20--detections--3--car--33.5--9x9--129.85v138.94",
    "percentage_probability": 33.47364962100983,
    "box_points": [
      129,
      85,
      138,
      94
    ]
  },
  "735-683-N--2020-05-05--13.29.20--detections--4--car--42.3--11x8--188.85v199.93": {
    "type": "car",
    "id": "735-683-N--2020-05-05--13.29.20--detections--4--car--42.3--11x8--188.85v199.93",
    "percentage_probability": 42.27093160152435,
    "box_points": [
      188,
      85,
      199,
      93
    ]
  },
  "735-683-N--2020-05-05--13.29.20--detections--5--car--55.4--19x19--156.96v175.115": {
    "type": "car",
    "id": "735-683-N--2020-05-05--13.29.20--detections--5--car--55.4--19x19--156.96v175.115",
    "percentage_probability": 55.42476177215576,
    "box_points": [
      156,
      96,
      175,
      115
    ]
  },
  "735-683-N--2020-05-05--13.29.20--detections--6--car--87.1--23x21--50.99v73.120": {
    "type": "car",
    "id": "735-683-N--2020-05-05--13.29.20--detections--6--car--87.1--23x21--50.99v73.120",
    "percentage_probability": 87.12412714958191,
    "box_points": [
      50,
      99,
      73,
      120
    ]
  },
  "735-683-N--2020-05-05--13.29.20--detections--7--bus--69.1--23x26--132.96v155.122": {
    "type": "bus",
    "id": "735-683-N--2020-05-05--13.29.20--detections--7--bus--69.1--23x26--132.96v155.122",
    "percentage_probability": 69.10173296928406,
    "box_points": [
      132,
      96,
      155,
      122
    ]
  },
  "735-683-N--2020-05-05--13.29.20--detections--8--car--35.9--23x25--132.96v155.121": {
    "type": "car",
    "id": "735-683-N--2020-05-05--13.29.20--detections--8--car--35.9--23x25--132.96v155.121",
    "percentage_probability": 35.89363992214203,
    "box_points": [
      132,
      96,
      155,
      121
    ]
  },
  "735-683-N--2020-05-05--13.29.20--detections--9--car--93.9--42x38--238.129v280.167": {
    "type": "car",
    "id": "735-683-N--2020-05-05--13.29.20--detections--9--car--93.9--42x38--238.129v280.167",
    "percentage_probability": 93.87853741645813,
    "box_points": [
      238,
      129,
      280,
      167
    ]
  },
  "735-683-N--2020-05-05--13.29.20--detections--10--car--77.5--84x54--266.185v350.239": {
    "type": "car",
    "id": "735-683-N--2020-05-05--13.29.20--detections--10--car--77.5--84x54--266.185v350.239",
    "percentage_probability": 77.48074531555176,
    "box_points": [
      266,
      185,
      350,
      239
    ]
  }
}
