{
  "id": "735-683-N--2020-05-05--13.53.58--detections",
  "model": "ResNet50_COCO_best_v2.0.1.h5",
  "summary": {
    "total": 18,
    "car": 16,
    "person": 1,
    "bus": 1
  },
  "735-683-N--2020-05-05--13.53.58--detections--1--car--35.0--9x9--192.81v201.90": {
    "type": "car",
    "id": "735-683-N--2020-05-05--13.53.58--detections--1--car--35.0--9x9--192.81v201.90",
    "percentage_probability": 34.992772340774536,
    "box_points": [
      192,
      81,
      201,
      90
    ]
  },
  "735-683-N--2020-05-05--13.53.58--detections--2--car--26.1--11x9--131.83v142.92": {
    "type": "car",
    "id": "735-683-N--2020-05-05--13.53.58--detections--2--car--26.1--11x9--131.83v142.92",
    "percentage_probability": 26.130717992782593,
    "box_points": [
      131,
      83,
      142,
      92
    ]
  },
  "735-683-N--2020-05-05--13.53.58--detections--3--car--42.7--12x10--119.84v131.94": {
    "type": "car",
    "id": "735-683-N--2020-05-05--13.53.58--detections--3--car--42.7--12x10--119.84v131.94",
    "percentage_probability": 42.71085858345032,
    "box_points": [
      119,
      84,
      131,
      94
    ]
  },
  "735-683-N--2020-05-05--13.53.58--detections--4--person--27.5--8x11--136.85v144.96": {
    "type": "person",
    "id": "735-683-N--2020-05-05--13.53.58--detections--4--person--27.5--8x11--136.85v144.96",
    "percentage_probability": 27.548915147781372,
    "box_points": [
      136,
      85,
      144,
      96
    ]
  },
  "735-683-N--2020-05-05--13.53.58--detections--5--car--25.5--14x18--143.87v157.105": {
    "type": "car",
    "id": "735-683-N--2020-05-05--13.53.58--detections--5--car--25.5--14x18--143.87v157.105",
    "percentage_probability": 25.515660643577576,
    "box_points": [
      143,
      87,
      157,
      105
    ]
  },
  "735-683-N--2020-05-05--13.53.58--detections--6--car--32.2--14x14--121.91v135.105": {
    "type": "car",
    "id": "735-683-N--2020-05-05--13.53.58--detections--6--car--32.2--14x14--121.91v135.105",
    "percentage_probability": 32.21459984779358,
    "box_points": [
      121,
      91,
      135,
      105
    ]
  },
  "735-683-N--2020-05-05--13.53.58--detections--7--car--26.6--13x8--125.93v138.101": {
    "type": "car",
    "id": "735-683-N--2020-05-05--13.53.58--detections--7--car--26.6--13x8--125.93v138.101",
    "percentage_probability": 26.64475440979004,
    "box_points": [
      125,
      93,
      138,
      101
    ]
  },
  "735-683-N--2020-05-05--13.53.58--detections--8--car--52.6--15x17--124.93v139.110": {
    "type": "car",
    "id": "735-683-N--2020-05-05--13.53.58--detections--8--car--52.6--15x17--124.93v139.110",
    "percentage_probability": 52.56928205490112,
    "box_points": [
      124,
      93,
      139,
      110
    ]
  },
  "735-683-N--2020-05-05--13.53.58--detections--9--car--68.1--16x14--63.99v79.113": {
    "type": "car",
    "id": "735-683-N--2020-05-05--13.53.58--detections--9--car--68.1--16x14--63.99v79.113",
    "percentage_probability": 68.07433366775513,
    "box_points": [
      63,
      99,
      79,
      113
    ]
  },
  "735-683-N--2020-05-05--13.53.58--detections--10--car--33.4--8x16--112.101v120.117": {
    "type": "car",
    "id": "735-683-N--2020-05-05--13.53.58--detections--10--car--33.4--8x16--112.101v120.117",
    "percentage_probability": 33.431994915008545,
    "box_points": [
      112,
      101,
      120,
      117
    ]
  },
  "735-683-N--2020-05-05--13.53.58--detections--11--car--28.1--9x11--124.99v133.110": {
    "type": "car",
    "id": "735-683-N--2020-05-05--13.53.58--detections--11--car--28.1--9x11--124.99v133.110",
    "percentage_probability": 28.076669573783875,
    "box_points": [
      124,
      99,
      133,
      110
    ]
  },
  "735-683-N--2020-05-05--13.53.58--detections--12--car--62.7--17x16--157.98v174.114": {
    "type": "car",
    "id": "735-683-N--2020-05-05--13.53.58--detections--12--car--62.7--17x16--157.98v174.114",
    "percentage_probability": 62.733882665634155,
    "box_points": [
      157,
      98,
      174,
      114
    ]
  },
  "735-683-N--2020-05-05--13.53.58--detections--13--car--35.6--18x17--127.95v145.112": {
    "type": "car",
    "id": "735-683-N--2020-05-05--13.53.58--detections--13--car--35.6--18x17--127.95v145.112",
    "percentage_probability": 35.6059193611145,
    "box_points": [
      127,
      95,
      145,
      112
    ]
  },
  "735-683-N--2020-05-05--13.53.58--detections--14--car--32.1--20x20--43.100v63.120": {
    "type": "car",
    "id": "735-683-N--2020-05-05--13.53.58--detections--14--car--32.1--20x20--43.100v63.120",
    "percentage_probability": 32.105553150177,
    "box_points": [
      43,
      100,
      63,
      120
    ]
  },
  "735-683-N--2020-05-05--13.53.58--detections--15--car--68.5--20x18--131.99v151.117": {
    "type": "car",
    "id": "735-683-N--2020-05-05--13.53.58--detections--15--car--68.5--20x18--131.99v151.117",
    "percentage_probability": 68.4891939163208,
    "box_points": [
      131,
      99,
      151,
      117
    ]
  },
  "735-683-N--2020-05-05--13.53.58--detections--16--bus--67.6--20x20--43.100v63.120": {
    "type": "bus",
    "id": "735-683-N--2020-05-05--13.53.58--detections--16--bus--67.6--20x20--43.100v63.120",
    "percentage_probability": 67.58219003677368,
    "box_points": [
      43,
      100,
      63,
      120
    ]
  },
  "735-683-N--2020-05-05--13.53.58--detections--17--car--74.4--26x27--173.103v199.130": {
    "type": "car",
    "id": "735-683-N--2020-05-05--13.53.58--detections--17--car--74.4--26x27--173.103v199.130",
    "percentage_probability": 74.37241077423096,
    "box_points": [
      173,
      103,
      199,
      130
    ]
  },
  "735-683-N--2020-05-05--13.53.58--detections--18--car--98.3--55x51--203.141v258.192": {
    "type": "car",
    "id": "735-683-N--2020-05-05--13.53.58--detections--18--car--98.3--55x51--203.141v258.192",
    "percentage_probability": 98.31161499023438,
    "box_points": [
      203,
      141,
      258,
      192
    ]
  }
}
